corax/__init__.py
corax/corax.py
corax-0.1.3.dist-info/AUTHORS.rst
corax-0.1.3.dist-info/LICENSE
corax-0.1.3.dist-info/METADATA
corax-0.1.3.dist-info/WHEEL
corax-0.1.3.dist-info/top_level.txt
corax-0.1.3.dist-info/RECORD
