Metadata-Version: 2.1
Name: corax
Version: 0.1.3
Summary: Corax is an OpenBalkans client implementation
Home-page: https://github.com/openbalkans/corax
Author: Barak Avrahami
Author-email: barak1345@gmail.com
License: MIT license
Keywords: corax
Platform: UNKNOWN
Classifier: Development Status :: 2 - Pre-Alpha
Classifier: Intended Audience :: Developers
Classifier: License :: OSI Approved :: MIT License
Classifier: Natural Language :: English
Classifier: Programming Language :: Python :: 3
Classifier: Programming Language :: Python :: 3.4
Classifier: Programming Language :: Python :: 3.5
Classifier: Programming Language :: Python :: 3.6
Classifier: Programming Language :: Python :: 3.7
Requires-Python: >=3
